odoo9_addon_medical_prescription-9.0.2.0.0-py2.7-nspkg.pth
odoo_addons/medical_prescription/__openerp__.py
odoo_addons/medical_prescription/__init__.py
odoo_addons/medical_prescription/README.rst
odoo_addons/medical_prescription/security/ir.model.access.csv
odoo_addons/medical_prescription/models/medical_prescription_order.py
odoo_addons/medical_prescription/models/medical_prescription_order_line.py
odoo_addons/medical_prescription/models/__init__.py
odoo_addons/medical_prescription/i18n/es_CO.po
odoo_addons/medical_prescription/i18n/pt_BR.po
odoo_addons/medical_prescription/views/medical_prescription_order_line_view.xml
odoo_addons/medical_prescription/views/medical_prescription_order_view.xml
odoo_addons/medical_prescription/views/medical_menu.xml
odoo_addons/medical_prescription/data/ir_sequence.xml
odoo_addons/medical_prescription/tests/test_medical_prescription_order.py
odoo_addons/medical_prescription/tests/test_medical_prescription_order_line.py
odoo_addons/medical_prescription/tests/__init__.py
odoo_addons/medical_prescription/demo/medical_prescription_order_line_demo.xml
odoo_addons/medical_prescription/demo/medical_patient_demo.xml
odoo_addons/medical_prescription/demo/medical_pharmacy_demo.xml
odoo_addons/medical_prescription/demo/medical_prescription_order_demo.xml
odoo_addons/medical_prescription/demo/medical_physician_demo.xml
odoo_addons/medical_prescription/static/description/icon.png
odoo9_addon_medical_prescription-9.0.2.0.0.dist-info/top_level.txt
odoo9_addon_medical_prescription-9.0.2.0.0.dist-info/WHEEL
odoo9_addon_medical_prescription-9.0.2.0.0.dist-info/RECORD
odoo9_addon_medical_prescription-9.0.2.0.0.dist-info/metadata.json
odoo9_addon_medical_prescription-9.0.2.0.0.dist-info/DESCRIPTION.rst
odoo9_addon_medical_prescription-9.0.2.0.0.dist-info/METADATA
odoo9_addon_medical_prescription-9.0.2.0.0.dist-info/namespace_packages.txt
