Metadata-Version: 2.0
Name: odoo9-addon-medical-prescription
Version: 9.0.2.0.0
Summary: Introduces prescription orders and prescription order lines.
Home-page: http://www.acsone.eu
Author: ACSONE SA/NV, LasLabs, Odoo Community Association (OCA)
Author-email: support@odoo-community.org
License: AGPL-3
Platform: UNKNOWN
Requires-Dist: odoo (<9.1a,>=9.0a)
Requires-Dist: odoo9-addon-medical-medication
Requires-Dist: odoo9-addon-medical-pharmacy
Classifier: Programming Language :: Python :: 2.7
Classifier: Framework :: Odoo
Classifier: License :: OSI Approved :: GNU Affero General Public License v3
